{
  "id": "law-doc-106763",
  "type": "statute",
  "title": "LEGE nr. 213 din 2 iunie 2009",
  "short_name": "lege 213 02 06 2009",
  "status": "in_force",
  "issued_date": "2009-06-02",
  "in_force_date": "2009-06-02",
  "url": "https://legislatie.just.ro/Public/DetaliiDocument/106763",
  "description": "Auto-ingested from Portal Legislativ LEGE corpus. Listing label: LEGE 213 02/06/2009",
  "provisions": [
    {
      "provision_ref": "Art.1",
      "section": "1",
      "title": "Articolul UNIC",
      "content": "Se aprobă Ordonanţa de urgenţă a Guvernului nr. 145 din 4 noiembrie 2008 pentru abrogarea Ordonanţei de urgenţă a Guvernului nr. 200/2000 privind clasificarea, etichetarea şi ambalarea substanţelor şi preparatelor chimice periculoase, publicată în Monitorul Oficial al României, Partea I, nr. 754 din 7 noiembrie 2008. Această lege a fost adoptată de Parlamentul României, cu respectarea prevederilor art. 75 şi ale art. 76 alin. (2) din Constituţia României, republicată. PREŞEDINTELE CAMEREI DEPUTAŢILOR ROBERTA ALMA ANASTASE PREŞEDINTELE SENATULUI MIRCEA-DAN GEOANĂ Bucureşti, 2 iunie 2009. Nr. 213. ----"
    }
  ],
  "definitions": []
}
