{
  "id": "law-doc-3109",
  "type": "statute",
  "title": "LEGE Nr. 30 din 26 mai 1993",
  "short_name": "lege 30 26 05 1993",
  "status": "in_force",
  "issued_date": "1993-05-26",
  "in_force_date": "1993-05-26",
  "url": "https://legislatie.just.ro/Public/DetaliiDocument/3109",
  "description": "Auto-ingested from Portal Legislativ LEGE corpus. Listing label: LEGE 30 26/05/1993",
  "provisions": [
    {
      "provision_ref": "Art.1",
      "section": "1",
      "title": "Articolul UNIC",
      "content": "Se ratifica Acordul dintre Guvernul României şi Guvernul Republicii Cipru privind promovarea şi protejarea reciprocă a investiţiilor, semnat la Bucureşti la 26 iulie 1991. Această lege a fost adoptată de Camera Deputaţilor în şedinţa din 22 martie 1993, cu respectarea prevederilor art. 74 alin. (2) din Constituţia României. PREŞEDINTELE CAMEREI DEPUTAŢILOR ADRIAN NASTASE Această lege a fost adoptată de Senat în şedinţa din 12 mai 1993, cu respectarea prevederilor art. 74 alin. (2) din Constituţia României. PREŞEDINTELE SENATULUI prof. univ. OLIVIU GHERMAN"
    }
  ],
  "definitions": []
}
