{
  "id": "law-doc-129467",
  "type": "statute",
  "title": "LEGE nr. 124 din 20 iunie 2011",
  "short_name": "lege 124 20 06 2011",
  "status": "in_force",
  "issued_date": "2011-06-20",
  "in_force_date": "2011-06-20",
  "url": "https://legislatie.just.ro/Public/DetaliiDocument/129467",
  "description": "Auto-ingested from Portal Legislativ LEGE corpus. Listing label: LEGE 124 20/06/2011",
  "provisions": [
    {
      "provision_ref": "Art.1",
      "section": "1",
      "title": "Articolul UNIC",
      "content": "La alineatul (1) al articolului 12 din Legea nr. 334/2006 privind finanţarea activităţii partidelor politice şi a campaniilor electorale, republicată în Monitorul Oficial al României, Partea I, nr. 510 din 22 iulie 2010, după litera g) se introduce o nouă literă, litera h), cu următorul cuprins: \"h) subînchirierea spaţiilor primite conform prevederilor art. 21 alin. (1) - (3), pentru organizarea birourilor parlamentare, fără ca valoarea chiriei lunare prevăzute în contractul de subînchiriere să depăşească valoarea chiriei lunare prevăzute în contractul de închiriere încheiat cu autorităţile locale. Cheltuielile de întreţinere aferente spaţiului subînchiriat revin biroului parlamentar, conform contractului încheiat.\" Această lege a fost adoptată de Parlamentul României, cu respectarea prevederilor art. 75 şi ale art. 76 alin. (1) din Constituţia României, republicată. PREŞEDINTELE CAMEREI DEPUTAŢILOR ROBERTA ALMA ANASTASE PREŞEDINTELE SENATULUI MIRCEA-DAN GEOANĂ Bucureşti, 20 iunie 2011. Nr. 124. -------"
    }
  ],
  "definitions": []
}
